__init__.py
Docker/create_envfiles.py
Docker/get_models.py
ansible/remove_old_tasks.py
ecips_controller/__init__.py
ecips_controller/ecips_fastapi/main.py
ecips_monitor/__init__.py
ecips_monitor/monitor_mpe.py
ecips_monitor/monitor_prlm.py
ecips_monitor/monitor_webapat.py
ecips_monitor/setup.py
ecips_serving/__init__.py
ecips_serving/models/dali_crop_gpu/5/dali.py
ecips_serving/models/dali_load_img/2/dali.py
ecips_serving/models/dali_preprocessing_hazmat/3/dali.py
ecips_serving/models/dali_preprocessing_yolov8/4/dali.py
ecips_serving/models/extract_crop_args/1/model.py
ecips_serving/models/network_test_model/1/model.py
ecips_serving/models/postprocessing_hazmat/1/model.py
ecips_serving/models/postprocessing_yolov8_no_segmentation/1/model.py
ecips_serving/models/postprocessing_yolov8_no_segmentation/2/model.py
ecips_serving/models/postprocessing_yolov8_segmentation/1/model.py
ecips_serving/models/reverse_img_extraction/1/model.py
ecips_serving/models/reverse_img_extraction/2/model.py
ecips_serving/models/shipping_label_ocr/1/model.py
ecips_serving/scripts/ensemble_test.py
ecips_serving/scripts/odtk_pipeline-lancos.py
ecips_serving/scripts/odtk_pipeline-linear.py
ecips_serving/scripts/odtk_pipeline.py
ecips_tasks/__init__.py
ecips_tasks/rebuild_db.py
ecips_tasks/setup.py
ecips_tasks/tasks.py
ecips_tasks/tasks_barcode.py
ecips_tasks/tasks_beats.py
ecips_tasks/tasks_comms.py
ecips_tasks/tasks_example.py
ecips_tasks/tasks_faissnv_v1.py
ecips_tasks/tasks_package.py
ecips_tasks/tasks_pvi.py
ecips_tasks/tasks_risks.py
ecips_tasks/tasks_stamp.py
ecips_tasks/tasks_triton.py
ecips_tasks/update_db.py
ecips_tasks/upgrade.py
ecips_tasks/cli/ecip-cli.py
ecips_tasks/cli/pull-detections.py
ecips_tasks/workflow/__init__.py
ecips_tasks/workflow/inference.py
ecips_tasks/workflow/prepare_data.py
ecips_tasks/workflow/validate_models.py
ecips_tasks/workflow/validate_results.py
ecips_testing/initialize_path.py
ecips_testing/setup.py
ecips_testing/fraud/run_fraud_task.py
ecip-0.0.1.dist-info/LICENSE
ecip-0.0.1.dist-info/METADATA
ecip-0.0.1.dist-info/WHEEL
ecip-0.0.1.dist-info/top_level.txt
ecip-0.0.1.dist-info/RECORD
