Metadata-Version: 2.1
Name: ecip
Version: 0.0.1
Summary: A python package for the USPS Ecip-Application
Author-email: David Lindenbaum <david.e.lindenbaum@usps.gov>, Emma Garvey <emma.r.garvey@usps.gov>, Mary Bollinger <mary.e.bollinger@usps.gov>
Project-URL: Homepage, https://github.usps.gov/eng/ecip-ECIP-Application.git
Project-URL: Bug Tracker, https://github.usps.gov/eng/ecip-ECIP-Application.git/issues
Classifier: Programming Language :: Python :: 3
Classifier: Operating System :: OS Independent
Requires-Python: >=3.7
License-File: LICENSE
